odoo/addons/product_search_multi_value/README.rst
odoo/addons/product_search_multi_value/__init__.py
odoo/addons/product_search_multi_value/__manifest__.py
odoo/addons/product_search_multi_value/data/search_field_data.xml
odoo/addons/product_search_multi_value/i18n/product_search_multi_value.pot
odoo/addons/product_search_multi_value/models/__init__.py
odoo/addons/product_search_multi_value/models/product_template.py
odoo/addons/product_search_multi_value/readme/CONFIGURE.rst
odoo/addons/product_search_multi_value/readme/CONTRIBUTORS.rst
odoo/addons/product_search_multi_value/readme/DESCRIPTION.rst
odoo/addons/product_search_multi_value/readme/ROADMAP.rst
odoo/addons/product_search_multi_value/readme/USAGE.rst
odoo/addons/product_search_multi_value/static/description/icon.png
odoo/addons/product_search_multi_value/static/description/index.html
odoo/addons/product_search_multi_value/tests/__init__.py
odoo/addons/product_search_multi_value/tests/test_product_search_multi_value.py
odoo/addons/product_search_multi_value/views/product_template_view.xml
odoo14_addon_product_search_multi_value-14.0.1.0.1.dist-info/METADATA
odoo14_addon_product_search_multi_value-14.0.1.0.1.dist-info/WHEEL
odoo14_addon_product_search_multi_value-14.0.1.0.1.dist-info/top_level.txt
odoo14_addon_product_search_multi_value-14.0.1.0.1.dist-info/RECORD
